Metadata-Version: 2.1
Name: odoo14-addon-l10n-fr-account-invoice-import-facturx
Version: 14.0.1.0.2
Summary: France-specific module to import Factur-X invoices
Home-page: https://github.com/OCA/l10n-france
Author: Akretion,Odoo Community Association (OCA)
Author-email: support@odoo-community.org
License: AGPL-3
Platform: UNKNOWN
Classifier: Programming Language :: Python
Classifier: Framework :: Odoo
Classifier: License :: OSI Approved :: GNU Affero General Public License v3
Requires-Python: >=3.6
Requires-Dist: odoo14-addon-account-invoice-import-facturx
Requires-Dist: odoo14-addon-l10n-fr-business-document-import
Requires-Dist: odoo (<14.1dev,>=14.0a)
